Workbook
Name Slicer_payment_mode: #N/A
Name Slicer_Product: #N/A
Name Slicer_Region: #N/A

Sheet Raw Data 
A1: Order_ID | B1: Order_Date | C1: Customer | D1: Region | E1: City | F1: Product | G1: Category | H1: Quantity | I1: Unit_Price | J1: Discount | K1: Payment_Mode | L1: Salesperson | M1: Gross Sales | N1: Discount AMT | O1: Net Sales
A2: ORD1001 | B2: 46235 | C2: Rahul Sharma | D2: North | E2: Delhi | F2: Laptop | G2: Electronics | H2: 1 | I2: 55000 | J2: 0.05 | K2: UPI | L2: Ankit | M2: =H2*I2 -> 55000 | N2: =M2*J2 -> 2750 | O2: =M2-N2 -> 52250
A3: ORD1002 | B3: 46236 | C3: Priya Singh | D3: North | E3: Gurgaon | F3: Mouse | G3: Accessories | H3: 3 | I3: 800 | J3: 0 | K3: Card | L3: Neha | M3: =H3*I3 -> 2400 | N3: =M3*J3 -> 0 | O3: =M3-N3 -> 2400
A4: ORD1003 | B4: 46237 | C4: Aman Verma | D4: West | E4: Mumbai | F4: Keyboard | G4: Accessories | H4: 2 | I4: 1500 | J4: 0.1 | K4: UPI | L4: Rohit | M4: =H4*I4 -> 3000 | N4: =M4*J4 -> 300 | O4: =M4-N4 -> 2700
A5: ORD1004 | B5: 46238 | C5: Simran Kaur | D5: North | E5: Delhi | F5: Monitor | G5: Electronics | H5: 1 | I5: 12500 | J5: 0.05 | K5: Cash | L5: Ankit | M5: =H5*I5 -> 12500 | N5: =M5*J5 -> 625 | O5: =M5-N5 -> 11875
A6: ORD1005 | B6: 46239 | C6: Arjun Mehta | D6: South | E6: Bangalore | F6: Laptop | G6: Electronics | H6: 2 | I6: 52000 | J6: 0.08 | K6: Card | L6: Priya | M6: =H6*I6 -> 104000 | N6: =M6*J6 -> 8320 | O6: =M6-N6 -> 95680
A7: ORD1006 | B7: 46240 | C7: Neha Gupta | D7: East | E7: Kolkata | F7: Headphones | G7: Accessories | H7: 4 | I7: 2200 | J7: 0.05 | K7: UPI | L7: Rohit | M7: =H7*I7 -> 8800 | N7: =M7*J7 -> 440 | O7: =M7-N7 -> 8360
A8: ORD1007 | B8: 46241 | C8: Karan Malhotra | D8: North | E8: Noida | F8: Printer | G8: Electronics | H8: 1 | I8: 14500 | J8: 0.1 | K8: Card | L8: Neha | M8: =H8*I8 -> 14500 | N8: =M8*J8 -> 1450 | O8: =M8-N8 -> 13050
A9: ORD1008 | B9: 46242 | C9: Riya Jain | D9: West | E9: Pune | F9: USB Cable | G9: Accessories | H9: 5 | I9: 450 | J9: 0 | K9: UPI | L9: Ankit | M9: =H9*I9 -> 2250 | N9: =M9*J9 -> 0 | O9: =M9-N9 -> 2250
A10: ORD1009 | B10: 46243 | C10: Vikas Yadav | D10: North | E10: Delhi | F10: Tablet | G10: Electronics | H10: 1 | I10: 28000 | J10: 0.07 | K10: Cash | L10: Priya | M10: =H10*I10 -> 28000 | N10: =M10*J10 -> 1960 | O10: =M10-N10 -> 26040
A11: ORD1010 | B11: 46244 | C11: Isha Kapoor | D11: South | E11: Chennai | F11: Keyboard | G11: Accessories | H11: 3 | I11: 1600 | J11: 0.05 | K11: UPI | L11: Rohit | M11: =H11*I11 -> 4800 | N11: =M11*J11 -> 240 | O11: =M11-N11 -> 4560
A12: ORD1011 | B12: 46245 | C12: Mohit Kumar | D12: East | E12: Kolkata | F12: Monitor | G12: Electronics | H12: 2 | I12: 11800 | J12: 0.1 | K12: Card | L12: Neha | M12: =H12*I12 -> 23600 | N12: =M12*J12 -> 2360 | O12: =M12-N12 -> 21240
A13: ORD1012 | B13: 46246 | C13: Sneha Arora | D13: North | E13: Gurgaon | F13: Mouse | G13: Accessories | H13: 6 | I13: 750 | J13: 0.05 | K13: UPI | L13: Ankit | M13: =H13*I13 -> 4500 | N13: =M13*J13 -> 225 | O13: =M13-N13 -> 4275
... A51: ORD1050 | B51: 46284 | C51: Yash Saini | D51: South | E51: Bangalore | F51: Mouse | G51: Accessories | H51: 7 | I51: 820 | J51: 0 | K51: UPI | L51: Rohit | M51: =H51*I51 -> 5740 | N51: =M51*J51 -> 0 | O51: =M51-N51 -> 5740
G53: qty sold | H53: =SUM(H1:H51) -> 129 | N53: sum | O53: =SUM(O2:O51) -> 1035533
N54: average | O54: =AVERAGE(O2:O51) -> 20710.66
N55: max order v | O55: =MAX(O2:O51) -> 102600
N56: min order value | O56: =MIN(O2:O51) -> 1520
C57: net sales in regions
C58: north | E58: =SUMIF(D2:D51,"north",O2:O51) -> 446058
C59: south | E59: =SUMIF(D2:D53,"south",O2:O51) -> 223765
C60: east | E60: =SUMIF(D2:D51,"east",O2:O51) -> 230680
C61: west | E61: =SUMIF(D2:D51,"west",O2:O51) -> 135030

Sheet Product Analysis 
A1: PRODUCT | B1: TOTAL QTY | C1: TOTAL NET SALES
A2: laptop | B2: =SUMIF('Raw Data '!F2:F51,"laptop",'Raw Data '!H2:H51) -> 10 | C2: =SUMIF('Raw Data '!F2:F51,"laptop",'Raw Data '!O2:O51) -> 518990
A3: mouse | B3: =SUMIF('Raw Data '!F2:F51,"mouse",'Raw Data '!H2:H51) -> 30 | C3: =SUMIF('Raw Data '!F2:F51,"mouse",'Raw Data '!O2:O51) -> 23375
A4: keyboard | B4: =SUMIF('Raw Data '!F2:F51,"keyboard",'Raw Data '!H2:H51) -> 14 | C4: =SUMIF('Raw Data '!F2:F51,"keyboard",'Raw Data '!O2:O51) -> 21255
A5: monitor | B5: =SUMIF('Raw Data '!F2:F51,"monitor",'Raw Data '!H2:H51) -> 10 | C5: =SUMIF('Raw Data '!F2:F51,"monitor",'Raw Data '!O2:O51) -> 112315
A6: headphones | B6: =SUMIF('Raw Data '!F2:F51,"headphones",'Raw Data '!H2:H51) -> 21 | C6: =SUMIF('Raw Data '!F2:F51,"headphones",'Raw Data '!O2:O51) -> 45315
A7: printer | B7: =SUMIF('Raw Data '!F2:F51,"printer",'Raw Data '!H2:H51) -> 7 | C7: =SUMIF('Raw Data '!F2:F51,"printer",'Raw Data '!O2:O51) -> 94978
A8: usb cables | B8: =SUMIF('Raw Data '!F2:F51,"usb cable",'Raw Data '!H2:H51) -> 29 | C8: =SUMIF('Raw Data '!F2:F51,"usb cable",'Raw Data '!O2:O51) -> 11295
A9: tablet | B9: =SUMIF('Raw Data '!F2:F51,"tablet",'Raw Data '!H2:H51) -> 8 | C9: =SUMIF('Raw Data '!F2:F51,"tablet",'Raw Data '!O2:O51) -> 208010
A11: max qty | B11: =MAX('Product Analysis '!B2:B9) -> 30 | C11: =MAX(C2:C9) -> 518990

Sheet Salesperson Analysis
A1: SALES PERSON | B1: TOTAL ORDER | C1: TOTAL NET SALES | D1: TOTAL AVERAGE SALES
A2: Ankit | B2: =COUNTIF('Raw Data '!L2:L51,"Ankit") -> 13 | C2: =SUMIF('Raw Data '!L2:L51,"Ankit",'Raw Data '!O2:O51) -> 190962 | D2: =AVERAGEIF('Raw Data '!L2:L51,"Ankit",'Raw Data '!O2:O51) -> 14689.385
A3: Neha | B3: =COUNTIF('Raw Data '!L2:L51,"Neha") -> 12 | C3: =SUMIF('Raw Data '!L2:L51,"Neha",'Raw Data '!O2:O51) -> 188436 | D3: =AVERAGEIF('Raw Data '!L2:L51,"Neha",'Raw Data '!O2:O51) -> 15703
A4: Rohit | B4: =COUNTIF('Raw Data '!L2:L51,"Rohit") -> 13 | C4: =SUMIF('Raw Data '!L2:L51,"Rohit",'Raw Data '!O2:O51) -> 195735 | D4: =AVERAGEIF('Raw Data '!L2:L51,"Rohit",'Raw Data '!O2:O51) -> 15056.538
A5: Priya | B5: =COUNTIF('Raw Data '!L2:L51,"Priya") -> 12 | C5: =SUMIF('Raw Data '!L2:L51,"Priya",'Raw Data '!O2:O51) -> 460400 | D5: =AVERAGEIF('Raw Data '!L2:L51,"Priya",'Raw Data '!O2:O51) -> 38366.667

Sheet Region pvc
A1: Row Labels | B1: Sum of Net Sales | C1: Sum of Quantity
A2: East | B2: 230680 | C2: 21 | D2: =GETPIVOTDATA("Sum of Net Sales ",$A$1,"Region","East")/GETPIVOTDATA("Sum of Quantity",$A$1,"Region","East") -> 10984.762
A3: North | B3: 446058 | C3: 40 | D3: =GETPIVOTDATA("Sum of Net Sales ",$A$1,"Region","North")/GETPIVOTDATA("Sum of Quantity",$A$1,"Region","North") -> 11151.45
A4: South | B4: 223765 | C4: 40 | D4: =GETPIVOTDATA("Sum of Net Sales ",$A$1,"Region","South")/GETPIVOTDATA("Sum of Quantity",$A$1,"Region","South") -> 5594.125
A5: West | B5: 135030 | C5: 28 | D5: =GETPIVOTDATA("Sum of Net Sales ",$A$1,"Region","West")/GETPIVOTDATA("Sum of Quantity",$A$1,"Region","West") -> 4822.5
A6: Grand Total | B6: 1035533 | C6: 129
B17: =GETPIVOTDATA("Sum of Net Sales ",$A$1,"Region","North")/GETPIVOTDATA("Sum of Net Sales ",$A$1)*100 -> 43.075209

Sheet Product pvc
A1: Row Labels | B1: Sum of Quantity | C1: Sum of Net Sales
A2: Headphones | B2: 21 | C2: 45315 | D2: =GETPIVOTDATA("Sum of Net Sales ",$A$1,"Product","Headphones")/GETPIVOTDATA("Sum of Quantity",$A$1,"Product","Headphones") -> 2157.8571
A3: Keyboard | B3: 14 | C3: 21255 | D3: =GETPIVOTDATA("Sum of Net Sales ",$A$1,"Product","Keyboard")/GETPIVOTDATA("Sum of Quantity",$A$1,"Product","Keyboard") -> 1518.2143
A4: Laptop | B4: 10 | C4: 518990 | D4: =GETPIVOTDATA("Sum of Net Sales ",$A$1,"Product","Laptop")/GETPIVOTDATA("Sum of Quantity",$A$1,"Product","Laptop") -> 51899
A5: Monitor | B5: 10 | C5: 112315 | D5: =GETPIVOTDATA("Sum of Net Sales ",$A$1,"Product","Monitor")/GETPIVOTDATA("Sum of Quantity",$A$1,"Product","Monitor") -> 11231.5
A6: Mouse | B6: 30 | C6: 23375 | D6: =GETPIVOTDATA("Sum of Net Sales ",$A$1,"Product","Mouse")/GETPIVOTDATA("Sum of Quantity",$A$1,"Product","Mouse") -> 779.16667
A7: Printer | B7: 7 | C7: 94978 | D7: =GETPIVOTDATA("Sum of Net Sales ",$A$1,"Product","Printer")/GETPIVOTDATA("Sum of Quantity",$A$1,"Product","Printer") -> 13568.286
A8: Tablet | B8: 8 | C8: 208010 | D8: =GETPIVOTDATA("Sum of Net Sales ",$A$1,"Product","Tablet")/GETPIVOTDATA("Sum of Quantity",$A$1,"Product","Tablet") -> 26001.25
A9: USB Cable | B9: 29 | C9: 11295 | D9: =GETPIVOTDATA("Sum of Net Sales ",$A$1,"Product","USB Cable")/GETPIVOTDATA("Sum of Quantity",$A$1,"Product","USB Cable") -> 389.48276
A10: Grand Total | B10: 129 | C10: 1035533

Sheet Salesperson pvc
A1: Row Labels | B1: Sum of TOTAL ORDER | C1: Sum of TOTAL NET SALES
A2: Ankit | B2: 13 | C2: 190962
A3: Neha | B3: 12 | C3: 188436
A4: Priya | B4: 12 | C4: 460400
A5: Rohit | B5: 13 | C5: 195735
A6: Grand Total | B6: 50 | C6: 1035533

Sheet Pay mode pvc
A1: Row Labels | B1: Sum of total order | C1: Sum of TOTAL NET SALES
A2: card | B2: 16 | C2: 585455
A3: cash | B3: 11 | C3: 188694
A4: upi | B4: 23 | C4: 261384
A5: Grand Total | B5: 50 | C5: 1035533

Sheet sale trend
A1: Row Labels | B1: Sum of Net Sales
A2: Aug | B2: 669771
A3: Sep | B3: 365762
A4: Grand Total | B4: 1035533

Sheet Dashboard
A1: SALES PERFORMANCE ANALYSIS
D3: August-September 2026
C5: SALES, ORDER & PRODUCT ANALYSIS
B8: REGION | E8: PRODUCT | I8: PAYMENT MODE
B16: TOTAL SALES | E16: TOTAL ORDERS | H16: TOTAL QUANTITY | K16: AVG ORDER
B17: 1035533 | E17: 50 | H17: 129 | K17: 20710.66
G20: MAIN ANALYSIS
G36: SECONDARY ANALYSIS
H55: TRENC

Sheet Sheet9
